avala/__init__.py
avala/cli.py
avala/exploit.py
avala/logging.py
avala/main.py
avala/py.typed
avala/api_client/__init__.py
avala/api_client/client.py
avala/api_client/schemas.py
avala/decorator/__init__.py
avala/decorator/decorator.py
avala/decorator/enums.py
avala/decorator/schemas.py
avala/storage/__init__.py
avala/storage/base.py
avala/storage/impl.py
avala_ad-0.1.0.dist-info/licenses/LICENCE
avala_ad-0.1.0.dist-info/METADATA
avala_ad-0.1.0.dist-info/WHEEL
avala_ad-0.1.0.dist-info/entry_points.txt
avala_ad-0.1.0.dist-info/top_level.txt
avala_ad-0.1.0.dist-info/RECORD
