Metadata-Version: 2.4
Name: avala-ad
Version: 0.1.0
Summary: Avala client for writing and running exploits
Author-email: Dušan Lazić <lazicdusan@protonmail.com>
License-Expression: GPL-3.0-or-later
Project-URL: Homepage, https://lazicdusan.com/avala
Requires-Python: >=3.11
License-File: LICENCE
Requires-Dist: apscheduler>=3.11.0
Requires-Dist: click>=8.2.1
Requires-Dist: httpx>=0.28.0
Requires-Dist: loguru>=0.7.2
Requires-Dist: pydantic>=2.10.2
Requires-Dist: redis[hiredis]>=5.2.1
Dynamic: license-file
